Metadata-Version: 2.1
Name: odoo-addon-company_default_partner_pricelist
Version: 16.0.1.0.0.5
Summary: Define default partner pricelist per company.
Home-page: https://github.com/OCA/partner-contact
Author: ForgeFlow, Odoo Community Association (OCA)
Author-email: support@odoo-community.org
License: LGPL-3
Classifier: Programming Language :: Python
Classifier: Framework :: Odoo
Classifier: Framework :: Odoo :: 16.0
Classifier: License :: OSI Approved :: GNU Lesser General Public License v3 (LGPLv3)
Requires-Python: >=3.10
Requires-Dist: odoo<16.1dev,>=16.0a
